easyfaiss/__init__.py
easyfaiss/vectorembeddings.py
easyfaiss/vectorspace.py
easyfaiss-0.1.5.dist-info/METADATA
easyfaiss-0.1.5.dist-info/WHEEL
easyfaiss-0.1.5.dist-info/RECORD
