Metadata-Version: 2.1
Name: easyfaiss
Version: 0.1.5
Summary: Package for building vector indexes
Home-page: https://github.com/Amar-89/easyfaiss
Author: Amar
Author-email: amar439412@gmail.com
Requires-Python: >=3.9,<3.12
Classifier: Programming Language :: Python :: 3
Classifier: Programming Language :: Python :: 3.9
Classifier: Programming Language :: Python :: 3.10
Classifier: Programming Language :: Python :: 3.11
Requires-Dist: faiss-cpu (>=1.7.4,<2.0.0)
Requires-Dist: numpy (>=1.26.1,<2.0.0)
Requires-Dist: torch (>=2.1.0,<3.0.0)
Requires-Dist: transformers (>=4.34.1,<5.0.0)
Project-URL: Repository, https://github.com/Amar-89/easyfaiss
